overload/__init__.py
overload/_lib.py
overload/test.py
hint_overload-0.0.0.dist-info/LICENSE
hint_overload-0.0.0.dist-info/METADATA
hint_overload-0.0.0.dist-info/WHEEL
hint_overload-0.0.0.dist-info/top_level.txt
hint_overload-0.0.0.dist-info/RECORD
