Metadata-Version: 2.1
Name: hint-overload
Version: 0.0.0
Summary: A project to allow overloading functions and methods based of the type hints
Author: RJ_Infinity
License: MIT License
Project-URL: Homepage, https://github.com/RJ-Infinity/overload
Project-URL: Documentation, https://github.com/RJ-Infinity/overload
Project-URL: Repository, https://github.com/RJ-Infinity/overload
Project-URL: Issues, https://github.com/RJ-Infinity/overload/issues
Keywords: overload,function overloading,type-hints,method overloading,multiple dispatch,dynamic dispatch
Classifier: Programming Language :: Python :: 3
Classifier: License :: OSI Approved :: MIT License
Classifier: Operating System :: OS Independent
Requires-Python: >=3.12
License-File: LICENSE
Requires-Dist: rj-type-hint-checker
